Metadata-Version: 2.4
Name: adafruit-circuitpython-ina228
Version: 2.0.3
Summary: CircuitPython driver for the INA228 I2C 85V, 20-bit High or Low Side Power Monitor
Author-email: Adafruit Industries <circuitpython@adafruit.com>
License: MIT
Project-URL: Homepage, https://github.com/adafruit/Adafruit_CircuitPython_INA228
Keywords: adafruit,blinka,circuitpython,micropython,ina228,power,monitor
Classifier: Intended Audience :: Developers
Classifier: Topic :: Software Development :: Libraries
Classifier: Topic :: Software Development :: Embedded Systems
Classifier: Topic :: System :: Hardware
Classifier: License :: OSI Approved :: MIT License
Classifier: Programming Language :: Python :: 3
License-File: LICENSE
Requires-Dist: Adafruit-Blinka
Requires-Dist: adafruit-circuitpython-busdevice
Requires-Dist: adafruit-circuitpython-register
Provides-Extra: optional
Dynamic: license-file
